{"type": "FeatureCollection", "features": [{"type": "Feature", "geometry": {"type": "Point", "coordinates": [-72.98362880000005, -41.31917129999998]}, "properties": {"FID_Lim_Co": 250, "REGION": "10", "NOM_REGION": "REGI\u00d3N DE LOS LAGOS", "PROVINCIA": "101", "NOM_PROVIN": "LLANQUIHUE", "COMUNA": "10109", "NOM_COMUNA": "PUERTO VARAS", "CUT": 10109, "FID_gis_os": 64545, "osm_id": "8939227678", "code": 2007, "fclass": "library", "name": "Qu\u00e9 Leo", "Propiedad": "fclass", "Valor": "library", "Clase": "Biblioteca", "Categor\u00eda": "P\u00fablico", "ID-Cat": 2000, "C\u00f3digo": 2007}}, {"type": "Feature", "geometry": {"type": "Point", "coordinates": [-72.98439559999998, -41.31781180000003]}, "properties": {"FID_Lim_Co": 250, "REGION": "10", "NOM_REGION": "REGI\u00d3N DE LOS LAGOS", "PROVINCIA": "101", "NOM_PROVIN": "LLANQUIHUE", "COMUNA": "10109", "NOM_COMUNA": "PUERTO VARAS", "CUT": 10109, "FID_gis_os": 24227, "osm_id": "4176579774", "code": 2007, "fclass": "library", "name": "Biblioteca Municipal Puerto Varas", "Propiedad": "fclass", "Valor": "library", "Clase": "Biblioteca", "Categor\u00eda": "P\u00fablico", "ID-Cat": 2000, "C\u00f3digo": 2007}}, {"type": "Feature", "geometry": {"type": "Point", "coordinates": [-72.98350979999998, -41.31684880000002]}, "properties": {"FID_Lim_Co": 250, "REGION": "10", "NOM_REGION": "REGI\u00d3N DE LOS LAGOS", "PROVINCIA": "101", "NOM_PROVIN": "LLANQUIHUE", "COMUNA": "10109", "NOM_COMUNA": "PUERTO VARAS", "CUT": 10109, "FID_gis_os": 33789, "osm_id": "4599840923", "code": 2007, "fclass": "library", "name": "Sotavento", "Propiedad": "fclass", "Valor": "library", "Clase": "Biblioteca", "Categor\u00eda": "P\u00fablico", "ID-Cat": 2000, "C\u00f3digo": 2007}}]}