{"type": "FeatureCollection", "features": [{"type": "Feature", "geometry": {"type": "Polygon", "coordinates": [[[-70.72629219999999, -33.36709739999998], [-70.72634100000005, -33.367067199999966], [-70.72638529999998, -33.36711720000001], [-70.72633650000003, -33.36714730000001], [-70.72629219999999, -33.36709739999998]]]}, "properties": {"FID_Lim_Co": 325, "REGION": "13", "NOM_REGION": "REGI\u00d3N METROPOLITANA DE SANTIAGO", "PROVINCIA": "131", "NOM_PROVIN": "SANTIAGO", "COMUNA": "13125", "NOM_COMUNA": "QUILICURA", "CUT": 13125, "FID_gis_os": 20695, "osm_id": "446139683", "code": 2518, "fclass": "beverages", "name": "Donde Lucy", "Propiedad": "fclass", "Valor": "beverages", "Clase": "Bebidas", "Categor\u00eda": "Compras", "ID-Cat": 2500, "C\u00f3digo": 2518}}, {"type": "Feature", "geometry": {"type": "Polygon", "coordinates": [[[-70.73841659999998, -33.368527700000016], [-70.7384039, -33.36839560000001], [-70.73851590000002, -33.368388100000004], [-70.73853210000003, -33.36855670000001], [-70.73846440000003, -33.36856130000004], [-70.73841659999998, -33.368527700000016]]]}, "properties": {"FID_Lim_Co": 325, "REGION": "13", "NOM_REGION": "REGI\u00d3N METROPOLITANA DE SANTIAGO", "PROVINCIA": "131", "NOM_PROVIN": "SANTIAGO", "COMUNA": "13125", "NOM_COMUNA": "QUILICURA", "CUT": 13125, "FID_gis_os": 20732, "osm_id": "446164904", "code": 2518, "fclass": "beverages", "name": "Botilleria Rosita", "Propiedad": "fclass", "Valor": "beverages", "Clase": "Bebidas", "Categor\u00eda": "Compras", "ID-Cat": 2500, "C\u00f3digo": 2518}}, {"type": "Feature", "geometry": {"type": "Polygon", "coordinates": [[[-70.7381259, -33.366774000000035], [-70.73814699999997, -33.36673080000001], [-70.73820589999995, -33.366724300000016], [-70.73823089999998, -33.36688210000001], [-70.73814450000003, -33.3668916], [-70.7381259, -33.366774000000035]]]}, "properties": {"FID_Lim_Co": 325, "REGION": "13", "NOM_REGION": "REGI\u00d3N METROPOLITANA DE SANTIAGO", "PROVINCIA": "131", "NOM_PROVIN": "SANTIAGO", "COMUNA": "13125", "NOM_COMUNA": "QUILICURA", "CUT": 13125, "FID_gis_os": 20735, "osm_id": "446167434", "code": 2518, "fclass": "beverages", "name": "Botiller\u00eda San Mart\u00edn", "Propiedad": "fclass", "Valor": "beverages", "Clase": "Bebidas", "Categor\u00eda": "Compras", "ID-Cat": 2500, "C\u00f3digo": 2518}}, {"type": "Feature", "geometry": {"type": "Polygon", "coordinates": [[[-70.73796129999997, -33.3657388], [-70.73806720000002, -33.36572060000001], [-70.73808340000002, -33.365786599999964], [-70.73797749999997, -33.365804799999964], [-70.73796129999997, -33.3657388]]]}, "properties": {"FID_Lim_Co": 325, "REGION": "13", "NOM_REGION": "REGI\u00d3N METROPOLITANA DE SANTIAGO", "PROVINCIA": "131", "NOM_PROVIN": "SANTIAGO", "COMUNA": "13125", "NOM_COMUNA": "QUILICURA", "CUT": 13125, "FID_gis_os": 20736, "osm_id": "446167436", "code": 2518, "fclass": "beverages", "name": "Nuria", "Propiedad": "fclass", "Valor": "beverages", "Clase": "Bebidas", "Categor\u00eda": "Compras", "ID-Cat": 2500, "C\u00f3digo": 2518}}, {"type": "Feature", "geometry": {"type": "Polygon", "coordinates": [[[-70.73973980000004, -33.36650240000004], [-70.73980749999996, -33.366492300000004], [-70.739822, -33.366559499999966], [-70.7397542, -33.366569700000014], [-70.73973980000004, -33.36650240000004]]]}, "properties": {"FID_Lim_Co": 325, "REGION": "13", "NOM_REGION": "REGI\u00d3N METROPOLITANA DE SANTIAGO", "PROVINCIA": "131", "NOM_PROVIN": "SANTIAGO", "COMUNA": "13125", "NOM_COMUNA": "QUILICURA", "CUT": 13125, "FID_gis_os": 20749, "osm_id": "446173129", "code": 2518, "fclass": "beverages", "name": "Don Leo", "Propiedad": "fclass", "Valor": "beverages", "Clase": "Bebidas", "Categor\u00eda": "Compras", "ID-Cat": 2500, "C\u00f3digo": 2518}}, {"type": "Feature", "geometry": {"type": "Polygon", "coordinates": [[[-70.73252339999999, -33.36499999999998], [-70.73252630000005, -33.36494450000001], [-70.73259030000001, -33.3649111], [-70.73258549999997, -33.3650023], [-70.73252339999999, -33.36499999999998]]]}, "properties": {"FID_Lim_Co": 325, "REGION": "13", "NOM_REGION": "REGI\u00d3N METROPOLITANA DE SANTIAGO", "PROVINCIA": "131", "NOM_PROVIN": "SANTIAGO", "COMUNA": "13125", "NOM_COMUNA": "QUILICURA", "CUT": 13125, "FID_gis_os": 20768, "osm_id": "446176989", "code": 2518, "fclass": "beverages", "name": "Premier", "Propiedad": "fclass", "Valor": "beverages", "Clase": "Bebidas", "Categor\u00eda": "Compras", "ID-Cat": 2500, "C\u00f3digo": 2518}}, {"type": "Feature", "geometry": {"type": "Polygon", "coordinates": [[[-70.72168100000002, -33.36657239999997], [-70.72177719999999, -33.36656000000001], [-70.72179209999999, -33.36663970000003], [-70.72169590000001, -33.3666522], [-70.72168100000002, -33.36657239999997]]]}, "properties": {"FID_Lim_Co": 325, "REGION": "13", "NOM_REGION": "REGI\u00d3N METROPOLITANA DE SANTIAGO", "PROVINCIA": "131", "NOM_PROVIN": "SANTIAGO", "COMUNA": "13125", "NOM_COMUNA": "QUILICURA", "CUT": 13125, "FID_gis_os": 20811, "osm_id": "446183914", "code": 2518, "fclass": "beverages", "name": "El Parr\u00f3n", "Propiedad": "fclass", "Valor": "beverages", "Clase": "Bebidas", "Categor\u00eda": "Compras", "ID-Cat": 2500, "C\u00f3digo": 2518}}, {"type": "Feature", "geometry": {"type": "Polygon", "coordinates": [[[-70.72582059999996, -33.365716999999975], [-70.72573450000004, -33.36573700000004], [-70.72569900000003, -33.36563079999995], [-70.72578509999997, -33.365610699999976], [-70.72579369999997, -33.36563629999996], [-70.72582059999996, -33.365716999999975]]]}, "properties": {"FID_Lim_Co": 325, "REGION": "13", "NOM_REGION": "REGI\u00d3N METROPOLITANA DE SANTIAGO", "PROVINCIA": "131", "NOM_PROVIN": "SANTIAGO", "COMUNA": "13125", "NOM_COMUNA": "QUILICURA", "CUT": 13125, "FID_gis_os": 20847, "osm_id": "446189829", "code": 2518, "fclass": "beverages", "name": "Botilleria El Alegre", "Propiedad": "fclass", "Valor": "beverages", "Clase": "Bebidas", "Categor\u00eda": "Compras", "ID-Cat": 2500, "C\u00f3digo": 2518}}]}