{"type": "FeatureCollection", "features": [{"type": "Feature", "geometry": {"type": "Point", "coordinates": [-72.63799210000005, -41.081282599999994]}, "properties": {"FID_Lim_Co": 81, "REGION": "10", "NOM_REGION": "REGI\u00d3N DE LOS LAGOS", "PROVINCIA": "103", "NOM_PROVIN": "OSORNO", "COMUNA": "10302", "NOM_COMUNA": "PUERTO OCTAY", "CUT": 10302, "FID_gis_os": 52709, "osm_id": "6364762889", "code": 2901, "fclass": "toilet", "name": "", "Propiedad": "fclass", "Valor": "toilet", "Clase": "Ba\u00f1o", "Categor\u00eda": "Punto de Inter\u00e9s", "ID-Cat": 2900, "C\u00f3digo": 2901}}]}