{"type": "FeatureCollection", "features": [{"type": "Feature", "geometry": {"type": "Polygon", "coordinates": [[[-70.99460510000003, -34.58605340000001], [-70.99454669999999, -34.58606579999997], [-70.99454329999998, -34.58605480000004], [-70.99451730000004, -34.58606029999996], [-70.99450120000003, -34.58600869999995], [-70.99452340000002, -34.58600400000001], [-70.99451439999999, -34.5859749], [-70.99457639999996, -34.58596130000003], [-70.99460510000003, -34.58605340000001]]]}, "properties": {"FID_Lim_Co": 270, "REGION": "6", "NOM_REGION": "REGI\u00d3N DEL LIBERTADOR GENERAL BERNARDO O'HIGGINS", "PROVINCIA": "63", "NOM_PROVIN": "COLCHAGUA", "COMUNA": "6301", "NOM_COMUNA": "SAN FERNANDO", "CUT": 6301, "FID_gis_os": 32666, "osm_id": "567214706", "code": 2129, "fclass": "veterinary", "name": "Versalles Clinica Veterinaria", "Propiedad": "fclass", "Valor": "veterinary", "Clase": "Veterinario", "Categor\u00eda": "Salud", "ID-Cat": 2100, "C\u00f3digo": 2129}}]}