{"type": "FeatureCollection", "features": [{"type": "Feature", "geometry": {"type": "Point", "coordinates": [-70.76257950000002, -33.63165529999996]}, "properties": {"FID_Lim_Co": 206, "REGION": "13", "NOM_REGION": "REGI\u00d3N METROPOLITANA DE SANTIAGO", "PROVINCIA": "134", "NOM_PROVIN": "MAIPO", "COMUNA": "13403", "NOM_COMUNA": "CALERA DE TANGO", "CUT": 13403, "FID_gis_os": 50315, "osm_id": "6141456931", "code": 2503, "fclass": "kiosk", "name": "", "Propiedad": "fclass", "Valor": "kiosk", "Clase": "Quiosco", "Categor\u00eda": "Compras", "ID-Cat": 2500, "C\u00f3digo": 2503}}, {"type": "Feature", "geometry": {"type": "Point", "coordinates": [-70.76492219999997, -33.63137519999997]}, "properties": {"FID_Lim_Co": 206, "REGION": "13", "NOM_REGION": "REGI\u00d3N METROPOLITANA DE SANTIAGO", "PROVINCIA": "134", "NOM_PROVIN": "MAIPO", "COMUNA": "13403", "NOM_COMUNA": "CALERA DE TANGO", "CUT": 13403, "FID_gis_os": 50313, "osm_id": "6141456929", "code": 2503, "fclass": "kiosk", "name": "", "Propiedad": "fclass", "Valor": "kiosk", "Clase": "Quiosco", "Categor\u00eda": "Compras", "ID-Cat": 2500, "C\u00f3digo": 2503}}, {"type": "Feature", "geometry": {"type": "Point", "coordinates": [-70.76599760000005, -33.631210300000006]}, "properties": {"FID_Lim_Co": 206, "REGION": "13", "NOM_REGION": "REGI\u00d3N METROPOLITANA DE SANTIAGO", "PROVINCIA": "134", "NOM_PROVIN": "MAIPO", "COMUNA": "13403", "NOM_COMUNA": "CALERA DE TANGO", "CUT": 13403, "FID_gis_os": 50309, "osm_id": "6141456925", "code": 2503, "fclass": "kiosk", "name": "Negocio Tio Julio", "Propiedad": "fclass", "Valor": "kiosk", "Clase": "Quiosco", "Categor\u00eda": "Compras", "ID-Cat": 2500, "C\u00f3digo": 2503}}, {"type": "Feature", "geometry": {"type": "Point", "coordinates": [-70.76343669999999, -33.631133100000014]}, "properties": {"FID_Lim_Co": 206, "REGION": "13", "NOM_REGION": "REGI\u00d3N METROPOLITANA DE SANTIAGO", "PROVINCIA": "134", "NOM_PROVIN": "MAIPO", "COMUNA": "13403", "NOM_COMUNA": "CALERA DE TANGO", "CUT": 13403, "FID_gis_os": 50316, "osm_id": "6141456936", "code": 2503, "fclass": "kiosk", "name": "", "Propiedad": "fclass", "Valor": "kiosk", "Clase": "Quiosco", "Categor\u00eda": "Compras", "ID-Cat": 2500, "C\u00f3digo": 2503}}, {"type": "Feature", "geometry": {"type": "Point", "coordinates": [-70.7661785, -33.63098649999996]}, "properties": {"FID_Lim_Co": 206, "REGION": "13", "NOM_REGION": "REGI\u00d3N METROPOLITANA DE SANTIAGO", "PROVINCIA": "134", "NOM_PROVIN": "MAIPO", "COMUNA": "13403", "NOM_COMUNA": "CALERA DE TANGO", "CUT": 13403, "FID_gis_os": 50310, "osm_id": "6141456926", "code": 2503, "fclass": "kiosk", "name": "Paty", "Propiedad": "fclass", "Valor": "kiosk", "Clase": "Quiosco", "Categor\u00eda": "Compras", "ID-Cat": 2500, "C\u00f3digo": 2503}}, {"type": "Feature", "geometry": {"type": "Point", "coordinates": [-70.76430369999996, -33.63093780000002]}, "properties": {"FID_Lim_Co": 206, "REGION": "13", "NOM_REGION": "REGI\u00d3N METROPOLITANA DE SANTIAGO", "PROVINCIA": "134", "NOM_PROVIN": "MAIPO", "COMUNA": "13403", "NOM_COMUNA": "CALERA DE TANGO", "CUT": 13403, "FID_gis_os": 50311, "osm_id": "6141456927", "code": 2503, "fclass": "kiosk", "name": "Ruti", "Propiedad": "fclass", "Valor": "kiosk", "Clase": "Quiosco", "Categor\u00eda": "Compras", "ID-Cat": 2500, "C\u00f3digo": 2503}}, {"type": "Feature", "geometry": {"type": "Point", "coordinates": [-70.76672669999996, -33.630335899999956]}, "properties": {"FID_Lim_Co": 206, "REGION": "13", "NOM_REGION": "REGI\u00d3N METROPOLITANA DE SANTIAGO", "PROVINCIA": "134", "NOM_PROVIN": "MAIPO", "COMUNA": "13403", "NOM_COMUNA": "CALERA DE TANGO", "CUT": 13403, "FID_gis_os": 50317, "osm_id": "6141456937", "code": 2503, "fclass": "kiosk", "name": "", "Propiedad": "fclass", "Valor": "kiosk", "Clase": "Quiosco", "Categor\u00eda": "Compras", "ID-Cat": 2500, "C\u00f3digo": 2503}}]}