{"type": "FeatureCollection", "features": [{"type": "Feature", "geometry": {"type": "Point", "coordinates": [-71.72365870000004, -46.53982120000003]}, "properties": {"FID_Lim_Co": 38, "REGION": "11", "NOM_REGION": "REGI\u00d3N DE AYS\u00c9N DEL GENERAL CARLOS IB\u00c1\u00d1EZ DEL CAMPO", "PROVINCIA": "114", "NOM_PROVIN": "GENERAL CARRERA", "COMUNA": "11401", "NOM_COMUNA": "CHILE CHICO", "CUT": 11401, "FID_gis_os": 40356, "osm_id": "5101285125", "code": 2101, "fclass": "pharmacy", "name": "FarmaAustral", "Propiedad": "fclass", "Valor": "pharmacy", "Clase": "Farmacia", "Categor\u00eda": "Salud", "ID-Cat": 2100, "C\u00f3digo": 2101}}]}