{"type": "FeatureCollection", "features": [{"type": "Feature", "geometry": {"type": "Point", "coordinates": [-73.02688159999997, -36.851942800000046]}, "properties": {"FID_Lim_Co": 329, "REGION": "8", "NOM_REGION": "REGI\u00d3N DEL BIOB\u00cdO", "PROVINCIA": "81", "NOM_PROVIN": "CONCEPCI\u00d3N", "COMUNA": "8101", "NOM_COMUNA": "CONCEPCI\u00d3N", "CUT": 8101, "FID_gis_os": 64747, "osm_id": "5706779964", "code": 4111, "fclass": "peak", "name": "", "Propiedad": "fclass", "Valor": "peak", "Clase": "Cumbre de Monta\u00f1a", "Categor\u00eda": "Natural", "ID-Cat": 4000, "C\u00f3digo": 4111}}, {"type": "Feature", "geometry": {"type": "Point", "coordinates": [-73.0035914, -36.84758489999999]}, "properties": {"FID_Lim_Co": 329, "REGION": "8", "NOM_REGION": "REGI\u00d3N DEL BIOB\u00cdO", "PROVINCIA": "81", "NOM_PROVIN": "CONCEPCI\u00d3N", "COMUNA": "8101", "NOM_COMUNA": "CONCEPCI\u00d3N", "CUT": 8101, "FID_gis_os": 64750, "osm_id": "5706779967", "code": 4111, "fclass": "peak", "name": "", "Propiedad": "fclass", "Valor": "peak", "Clase": "Cumbre de Monta\u00f1a", "Categor\u00eda": "Natural", "ID-Cat": 4000, "C\u00f3digo": 4111}}, {"type": "Feature", "geometry": {"type": "Point", "coordinates": [-72.87151129999998, -36.84517330000002]}, "properties": {"FID_Lim_Co": 329, "REGION": "8", "NOM_REGION": "REGI\u00d3N DEL BIOB\u00cdO", "PROVINCIA": "81", "NOM_PROVIN": "CONCEPCI\u00d3N", "COMUNA": "8101", "NOM_COMUNA": "CONCEPCI\u00d3N", "CUT": 8101, "FID_gis_os": 66519, "osm_id": "5726391123", "code": 4111, "fclass": "peak", "name": "", "Propiedad": "fclass", "Valor": "peak", "Clase": "Cumbre de Monta\u00f1a", "Categor\u00eda": "Natural", "ID-Cat": 4000, "C\u00f3digo": 4111}}, {"type": "Feature", "geometry": {"type": "Point", "coordinates": [-73.03812599999998, -36.84219230000002]}, "properties": {"FID_Lim_Co": 329, "REGION": "8", "NOM_REGION": "REGI\u00d3N DEL BIOB\u00cdO", "PROVINCIA": "81", "NOM_PROVIN": "CONCEPCI\u00d3N", "COMUNA": "8101", "NOM_COMUNA": "CONCEPCI\u00d3N", "CUT": 8101, "FID_gis_os": 5668, "osm_id": "2612196499", "code": 4111, "fclass": "peak", "name": "Cerro Caracol", "Propiedad": "fclass", "Valor": "peak", "Clase": "Cumbre de Monta\u00f1a", "Categor\u00eda": "Natural", "ID-Cat": 4000, "C\u00f3digo": 4111}}, {"type": "Feature", "geometry": {"type": "Point", "coordinates": [-73.05320149999997, -36.83676630000004]}, "properties": {"FID_Lim_Co": 329, "REGION": "8", "NOM_REGION": "REGI\u00d3N DEL BIOB\u00cdO", "PROVINCIA": "81", "NOM_PROVIN": "CONCEPCI\u00d3N", "COMUNA": "8101", "NOM_COMUNA": "CONCEPCI\u00d3N", "CUT": 8101, "FID_gis_os": 64753, "osm_id": "5706779970", "code": 4111, "fclass": "peak", "name": "Cerro La Cruz", "Propiedad": "fclass", "Valor": "peak", "Clase": "Cumbre de Monta\u00f1a", "Categor\u00eda": "Natural", "ID-Cat": 4000, "C\u00f3digo": 4111}}, {"type": "Feature", "geometry": {"type": "Point", "coordinates": [-73.02685579999996, -36.82395719999999]}, "properties": {"FID_Lim_Co": 329, "REGION": "8", "NOM_REGION": "REGI\u00d3N DEL BIOB\u00cdO", "PROVINCIA": "81", "NOM_PROVIN": "CONCEPCI\u00d3N", "COMUNA": "8101", "NOM_COMUNA": "CONCEPCI\u00d3N", "CUT": 8101, "FID_gis_os": 64748, "osm_id": "5706779965", "code": 4111, "fclass": "peak", "name": "Cerro La Virgen", "Propiedad": "fclass", "Valor": "peak", "Clase": "Cumbre de Monta\u00f1a", "Categor\u00eda": "Natural", "ID-Cat": 4000, "C\u00f3digo": 4111}}, {"type": "Feature", "geometry": {"type": "Point", "coordinates": [-73.05589550000002, -36.82284479999996]}, "properties": {"FID_Lim_Co": 329, "REGION": "8", "NOM_REGION": "REGI\u00d3N DEL BIOB\u00cdO", "PROVINCIA": "81", "NOM_PROVIN": "CONCEPCI\u00d3N", "COMUNA": "8101", "NOM_COMUNA": "CONCEPCI\u00d3N", "CUT": 8101, "FID_gis_os": 115511, "osm_id": "7447350793", "code": 4111, "fclass": "peak", "name": "Cerro Amarillo", "Propiedad": "fclass", "Valor": "peak", "Clase": "Cumbre de Monta\u00f1a", "Categor\u00eda": "Natural", "ID-Cat": 4000, "C\u00f3digo": 4111}}, {"type": "Feature", "geometry": {"type": "Point", "coordinates": [-73.06987449999997, -36.82167430000001]}, "properties": {"FID_Lim_Co": 329, "REGION": "8", "NOM_REGION": "REGI\u00d3N DEL BIOB\u00cdO", "PROVINCIA": "81", "NOM_PROVIN": "CONCEPCI\u00d3N", "COMUNA": "8101", "NOM_COMUNA": "CONCEPCI\u00d3N", "CUT": 8101, "FID_gis_os": 4630, "osm_id": "1964962758", "code": 4111, "fclass": "peak", "name": "Cerro Chepe", "Propiedad": "fclass", "Valor": "peak", "Clase": "Cumbre de Monta\u00f1a", "Categor\u00eda": "Natural", "ID-Cat": 4000, "C\u00f3digo": 4111}}, {"type": "Feature", "geometry": {"type": "Point", "coordinates": [-73.03816100000003, -36.81031630000003]}, "properties": {"FID_Lim_Co": 329, "REGION": "8", "NOM_REGION": "REGI\u00d3N DEL BIOB\u00cdO", "PROVINCIA": "81", "NOM_PROVIN": "CONCEPCI\u00d3N", "COMUNA": "8101", "NOM_COMUNA": "CONCEPCI\u00d3N", "CUT": 8101, "FID_gis_os": 4628, "osm_id": "1964962756", "code": 4111, "fclass": "peak", "name": "Cerro La P\u00f3lvora", "Propiedad": "fclass", "Valor": "peak", "Clase": "Cumbre de Monta\u00f1a", "Categor\u00eda": "Natural", "ID-Cat": 4000, "C\u00f3digo": 4111}}, {"type": "Feature", "geometry": {"type": "Point", "coordinates": [-73.0646385, -36.80985319999999]}, "properties": {"FID_Lim_Co": 329, "REGION": "8", "NOM_REGION": "REGI\u00d3N DEL BIOB\u00cdO", "PROVINCIA": "81", "NOM_PROVIN": "CONCEPCI\u00d3N", "COMUNA": "8101", "NOM_COMUNA": "CONCEPCI\u00d3N", "CUT": 8101, "FID_gis_os": 64751, "osm_id": "5706779968", "code": 4111, "fclass": "peak", "name": "", "Propiedad": "fclass", "Valor": "peak", "Clase": "Cumbre de Monta\u00f1a", "Categor\u00eda": "Natural", "ID-Cat": 4000, "C\u00f3digo": 4111}}, {"type": "Feature", "geometry": {"type": "Point", "coordinates": [-73.00618879999999, -36.80308240000004]}, "properties": {"FID_Lim_Co": 329, "REGION": "8", "NOM_REGION": "REGI\u00d3N DEL BIOB\u00cdO", "PROVINCIA": "81", "NOM_PROVIN": "CONCEPCI\u00d3N", "COMUNA": "8101", "NOM_COMUNA": "CONCEPCI\u00d3N", "CUT": 8101, "FID_gis_os": 64754, "osm_id": "5706780436", "code": 4111, "fclass": "peak", "name": "Cerro El Manzano", "Propiedad": "fclass", "Valor": "peak", "Clase": "Cumbre de Monta\u00f1a", "Categor\u00eda": "Natural", "ID-Cat": 4000, "C\u00f3digo": 4111}}, {"type": "Feature", "geometry": {"type": "Point", "coordinates": [-73.0528497, -36.80286489999999]}, "properties": {"FID_Lim_Co": 329, "REGION": "8", "NOM_REGION": "REGI\u00d3N DEL BIOB\u00cdO", "PROVINCIA": "81", "NOM_PROVIN": "CONCEPCI\u00d3N", "COMUNA": "8101", "NOM_COMUNA": "CONCEPCI\u00d3N", "CUT": 8101, "FID_gis_os": 4629, "osm_id": "1964962757", "code": 4111, "fclass": "peak", "name": "Chacabuco", "Propiedad": "fclass", "Valor": "peak", "Clase": "Cumbre de Monta\u00f1a", "Categor\u00eda": "Natural", "ID-Cat": 4000, "C\u00f3digo": 4111}}, {"type": "Feature", "geometry": {"type": "Point", "coordinates": [-73.0405426, -36.796536899999985]}, "properties": {"FID_Lim_Co": 329, "REGION": "8", "NOM_REGION": "REGI\u00d3N DEL BIOB\u00cdO", "PROVINCIA": "81", "NOM_PROVIN": "CONCEPCI\u00d3N", "COMUNA": "8101", "NOM_COMUNA": "CONCEPCI\u00d3N", "CUT": 8101, "FID_gis_os": 64752, "osm_id": "5706779969", "code": 4111, "fclass": "peak", "name": "Cerro Lo Galindo", "Propiedad": "fclass", "Valor": "peak", "Clase": "Cumbre de Monta\u00f1a", "Categor\u00eda": "Natural", "ID-Cat": 4000, "C\u00f3digo": 4111}}, {"type": "Feature", "geometry": {"type": "Point", "coordinates": [-73.06026110000002, -36.79524820000003]}, "properties": {"FID_Lim_Co": 329, "REGION": "8", "NOM_REGION": "REGI\u00d3N DEL BIOB\u00cdO", "PROVINCIA": "81", "NOM_PROVIN": "CONCEPCI\u00d3N", "COMUNA": "8101", "NOM_COMUNA": "CONCEPCI\u00d3N", "CUT": 8101, "FID_gis_os": 64749, "osm_id": "5706779966", "code": 4111, "fclass": "peak", "name": "Cerro Las Monjas", "Propiedad": "fclass", "Valor": "peak", "Clase": "Cumbre de Monta\u00f1a", "Categor\u00eda": "Natural", "ID-Cat": 4000, "C\u00f3digo": 4111}}, {"type": "Feature", "geometry": {"type": "Point", "coordinates": [-72.98125430000005, -36.780537400000014]}, "properties": {"FID_Lim_Co": 329, "REGION": "8", "NOM_REGION": "REGI\u00d3N DEL BIOB\u00cdO", "PROVINCIA": "81", "NOM_PROVIN": "CONCEPCI\u00d3N", "COMUNA": "8101", "NOM_COMUNA": "CONCEPCI\u00d3N", "CUT": 8101, "FID_gis_os": 65653, "osm_id": "5716066052", "code": 4111, "fclass": "peak", "name": "", "Propiedad": "fclass", "Valor": "peak", "Clase": "Cumbre de Monta\u00f1a", "Categor\u00eda": "Natural", "ID-Cat": 4000, "C\u00f3digo": 4111}}]}