{"type": "FeatureCollection", "features": [{"type": "Feature", "geometry": {"type": "Polygon", "coordinates": [[[-73.03082519999995, -40.46449290000004], [-73.03115250000003, -40.46412550000001], [-73.0313721, -40.46449649999998], [-73.03105050000002, -40.464843800000025], [-73.03082519999995, -40.46449290000004]]]}, "properties": {"FID_Lim_Co": 94, "REGION": "10", "NOM_REGION": "REGI\u00d3N DE LOS LAGOS", "PROVINCIA": "103", "NOM_PROVIN": "OSORNO", "COMUNA": "10307", "NOM_COMUNA": "SAN PABLO", "CUT": 10307, "FID_gis_os": 1715, "osm_id": "336858858", "code": 5260, "fclass": "parking", "name": "", "Propiedad": "fclass", "Valor": "parking", "Clase": "Estacionamiento", "Categor\u00eda": "Combustible y Estacionamiento", "ID-Cat": 5200, "C\u00f3digo": 5260}}, {"type": "Feature", "geometry": {"type": "Polygon", "coordinates": [[[-73.03544100000003, -40.47705589999998], [-73.03588090000002, -40.477974], [-73.03617600000001, -40.47811680000001], [-73.0361491, -40.47828000000001], [-73.03490999999997, -40.47861869999997], [-73.03458269999999, -40.47783929999996], [-73.03544100000003, -40.47705589999998]], [[-73.03478129999999, -40.47787609999999], [-73.03496809999999, -40.4782316], [-73.03514340000001, -40.47807190000002], [-73.03497439999998, -40.47769649999996], [-73.03478129999999, -40.47787609999999]], [[-73.03549199999999, -40.478078100000005], [-73.03559929999999, -40.478086199999964], [-73.03544109999996, -40.47771489999997], [-73.03532879999999, -40.47771330000002], [-73.03549199999999, -40.478078100000005]]]}, "properties": {"FID_Lim_Co": 94, "REGION": "10", "NOM_REGION": "REGI\u00d3N DE LOS LAGOS", "PROVINCIA": "103", "NOM_PROVIN": "OSORNO", "COMUNA": "10307", "NOM_COMUNA": "SAN PABLO", "CUT": 10307, "FID_gis_os": 4869, "osm_id": "706162459", "code": 5251, "fclass": "service", "name": "", "Propiedad": "fclass", "Valor": "service", "Clase": "Servicio", "Categor\u00eda": "Combustible y Estacionamiento", "ID-Cat": 5200, "C\u00f3digo": 5251}}, {"type": "Feature", "geometry": {"type": "Polygon", "coordinates": [[[-73.03478129999999, -40.47787609999999], [-73.03497439999998, -40.47769649999996], [-73.03514340000001, -40.47807190000002], [-73.03496809999999, -40.4782316], [-73.03478129999999, -40.47787609999999]]]}, "properties": {"FID_Lim_Co": 94, "REGION": "10", "NOM_REGION": "REGI\u00d3N DE LOS LAGOS", "PROVINCIA": "103", "NOM_PROVIN": "OSORNO", "COMUNA": "10307", "NOM_COMUNA": "SAN PABLO", "CUT": 10307, "FID_gis_os": 863, "osm_id": "211565329", "code": 5260, "fclass": "parking", "name": "", "Propiedad": "fclass", "Valor": "parking", "Clase": "Estacionamiento", "Categor\u00eda": "Combustible y Estacionamiento", "ID-Cat": 5200, "C\u00f3digo": 5260}}, {"type": "Feature", "geometry": {"type": "Polygon", "coordinates": [[[-73.03478129999999, -40.47787609999999], [-73.03497439999998, -40.47769649999996], [-73.03514340000001, -40.47807190000002], [-73.03496809999999, -40.4782316], [-73.03478129999999, -40.47787609999999]]]}, "properties": {"FID_Lim_Co": 94, "REGION": "10", "NOM_REGION": "REGI\u00d3N DE LOS LAGOS", "PROVINCIA": "103", "NOM_PROVIN": "OSORNO", "COMUNA": "10307", "NOM_COMUNA": "SAN PABLO", "CUT": 10307, "FID_gis_os": 4869, "osm_id": "706162459", "code": 5251, "fclass": "service", "name": "", "Propiedad": "fclass", "Valor": "service", "Clase": "Servicio", "Categor\u00eda": "Combustible y Estacionamiento", "ID-Cat": 5200, "C\u00f3digo": 5251}}, {"type": "Feature", "geometry": {"type": "Polygon", "coordinates": [[[-73.03549199999999, -40.478078100000005], [-73.03532879999999, -40.47771330000002], [-73.03544109999996, -40.47771489999997], [-73.03559929999999, -40.478086199999964], [-73.03549199999999, -40.478078100000005]]]}, "properties": {"FID_Lim_Co": 94, "REGION": "10", "NOM_REGION": "REGI\u00d3N DE LOS LAGOS", "PROVINCIA": "103", "NOM_PROVIN": "OSORNO", "COMUNA": "10307", "NOM_COMUNA": "SAN PABLO", "CUT": 10307, "FID_gis_os": 864, "osm_id": "211565333", "code": 5260, "fclass": "parking", "name": "Copec", "Propiedad": "fclass", "Valor": "parking", "Clase": "Estacionamiento", "Categor\u00eda": "Combustible y Estacionamiento", "ID-Cat": 5200, "C\u00f3digo": 5260}}, {"type": "Feature", "geometry": {"type": "Polygon", "coordinates": [[[-73.03549199999999, -40.478078100000005], [-73.03532879999999, -40.47771330000002], [-73.03544109999996, -40.47771489999997], [-73.03559929999999, -40.478086199999964], [-73.03549199999999, -40.478078100000005]]]}, "properties": {"FID_Lim_Co": 94, "REGION": "10", "NOM_REGION": "REGI\u00d3N DE LOS LAGOS", "PROVINCIA": "103", "NOM_PROVIN": "OSORNO", "COMUNA": "10307", "NOM_COMUNA": "SAN PABLO", "CUT": 10307, "FID_gis_os": 4869, "osm_id": "706162459", "code": 5251, "fclass": "service", "name": "", "Propiedad": "fclass", "Valor": "service", "Clase": "Servicio", "Categor\u00eda": "Combustible y Estacionamiento", "ID-Cat": 5200, "C\u00f3digo": 5251}}]}