{"type": "FeatureCollection", "features": [{"type": "Feature", "geometry": {"type": "Point", "coordinates": [-71.83724199999997, -34.76965649999997]}, "properties": {"FID_Lim_Co": 50, "REGION": "6", "NOM_REGION": "REGI\u00d3N DEL LIBERTADOR GENERAL BERNARDO O'HIGGINS", "PROVINCIA": "62", "NOM_PROVIN": "CARDENAL CARO", "COMUNA": "6206", "NOM_COMUNA": "PAREDONES", "CUT": 6206, "FID_gis_os": 20342, "osm_id": "3653718701", "code": 2001, "fclass": "police", "name": "Reten San Pedro de Alcantara", "Propiedad": "fclass", "Valor": "police", "Clase": "Polic\u00eda", "Categor\u00eda": "P\u00fablico", "ID-Cat": 2000, "C\u00f3digo": 2001}}, {"type": "Feature", "geometry": {"type": "Point", "coordinates": [-71.89938329999998, -34.64862950000001]}, "properties": {"FID_Lim_Co": 50, "REGION": "6", "NOM_REGION": "REGI\u00d3N DEL LIBERTADOR GENERAL BERNARDO O'HIGGINS", "PROVINCIA": "62", "NOM_PROVIN": "CARDENAL CARO", "COMUNA": "6206", "NOM_COMUNA": "PAREDONES", "CUT": 6206, "FID_gis_os": 20338, "osm_id": "3653697211", "code": 2001, "fclass": "police", "name": "Reten Paredones", "Propiedad": "fclass", "Valor": "police", "Clase": "Polic\u00eda", "Categor\u00eda": "P\u00fablico", "ID-Cat": 2000, "C\u00f3digo": 2001}}]}