{"type": "FeatureCollection", "features": [{"type": "Feature", "geometry": {"type": "Point", "coordinates": [-72.61409949999998, -37.736684699999984]}, "properties": {"FID_Lim_Co": 98, "REGION": "9", "NOM_REGION": "REGI\u00d3N DE LA ARAUCAN\u00cdA", "PROVINCIA": "92", "NOM_PROVIN": "MALLECO", "COMUNA": "9209", "NOM_COMUNA": "RENAICO", "CUT": 9209, "FID_gis_os": 44418, "osm_id": "7650127397", "code": 5203, "fclass": "stop", "name": "", "Propiedad": "fclass", "Valor": "stop", "Clase": "Se\u00f1al de Alto", "Categor\u00eda": "Tr\u00e1fico", "ID-Cat": 5200, "C\u00f3digo": 5203}}, {"type": "Feature", "geometry": {"type": "Point", "coordinates": [-72.61411869999996, -37.736569]}, "properties": {"FID_Lim_Co": 98, "REGION": "9", "NOM_REGION": "REGI\u00d3N DE LA ARAUCAN\u00cdA", "PROVINCIA": "92", "NOM_PROVIN": "MALLECO", "COMUNA": "9209", "NOM_COMUNA": "RENAICO", "CUT": 9209, "FID_gis_os": 55188, "osm_id": "8293438202", "code": 5203, "fclass": "stop", "name": "", "Propiedad": "fclass", "Valor": "stop", "Clase": "Se\u00f1al de Alto", "Categor\u00eda": "Tr\u00e1fico", "ID-Cat": 5200, "C\u00f3digo": 5203}}, {"type": "Feature", "geometry": {"type": "Point", "coordinates": [-72.61431529999999, -37.73638550000001]}, "properties": {"FID_Lim_Co": 98, "REGION": "9", "NOM_REGION": "REGI\u00d3N DE LA ARAUCAN\u00cdA", "PROVINCIA": "92", "NOM_PROVIN": "MALLECO", "COMUNA": "9209", "NOM_COMUNA": "RENAICO", "CUT": 9209, "FID_gis_os": 55186, "osm_id": "8293438190", "code": 5203, "fclass": "stop", "name": "", "Propiedad": "fclass", "Valor": "stop", "Clase": "Se\u00f1al de Alto", "Categor\u00eda": "Tr\u00e1fico", "ID-Cat": 5200, "C\u00f3digo": 5203}}, {"type": "Feature", "geometry": {"type": "Point", "coordinates": [-72.61420549999995, -37.73637859999997]}, "properties": {"FID_Lim_Co": 98, "REGION": "9", "NOM_REGION": "REGI\u00d3N DE LA ARAUCAN\u00cdA", "PROVINCIA": "92", "NOM_PROVIN": "MALLECO", "COMUNA": "9209", "NOM_COMUNA": "RENAICO", "CUT": 9209, "FID_gis_os": 55187, "osm_id": "8293438192", "code": 5203, "fclass": "stop", "name": "", "Propiedad": "fclass", "Valor": "stop", "Clase": "Se\u00f1al de Alto", "Categor\u00eda": "Tr\u00e1fico", "ID-Cat": 5200, "C\u00f3digo": 5203}}, {"type": "Feature", "geometry": {"type": "Point", "coordinates": [-72.5906802, -37.67598179999997]}, "properties": {"FID_Lim_Co": 98, "REGION": "9", "NOM_REGION": "REGI\u00d3N DE LA ARAUCAN\u00cdA", "PROVINCIA": "92", "NOM_PROVIN": "MALLECO", "COMUNA": "9209", "NOM_COMUNA": "RENAICO", "CUT": 9209, "FID_gis_os": 56833, "osm_id": "8391821949", "code": 5203, "fclass": "stop", "name": "", "Propiedad": "fclass", "Valor": "stop", "Clase": "Se\u00f1al de Alto", "Categor\u00eda": "Tr\u00e1fico", "ID-Cat": 5200, "C\u00f3digo": 5203}}, {"type": "Feature", "geometry": {"type": "Point", "coordinates": [-72.589155, -37.67053849999998]}, "properties": {"FID_Lim_Co": 98, "REGION": "9", "NOM_REGION": "REGI\u00d3N DE LA ARAUCAN\u00cdA", "PROVINCIA": "92", "NOM_PROVIN": "MALLECO", "COMUNA": "9209", "NOM_COMUNA": "RENAICO", "CUT": 9209, "FID_gis_os": 55444, "osm_id": "8302848859", "code": 5203, "fclass": "stop", "name": "", "Propiedad": "fclass", "Valor": "stop", "Clase": "Se\u00f1al de Alto", "Categor\u00eda": "Tr\u00e1fico", "ID-Cat": 5200, "C\u00f3digo": 5203}}, {"type": "Feature", "geometry": {"type": "Point", "coordinates": [-72.58947280000001, -37.670480100000034]}, "properties": {"FID_Lim_Co": 98, "REGION": "9", "NOM_REGION": "REGI\u00d3N DE LA ARAUCAN\u00cdA", "PROVINCIA": "92", "NOM_PROVIN": "MALLECO", "COMUNA": "9209", "NOM_COMUNA": "RENAICO", "CUT": 9209, "FID_gis_os": 55443, "osm_id": "8302848857", "code": 5203, "fclass": "stop", "name": "", "Propiedad": "fclass", "Valor": "stop", "Clase": "Se\u00f1al de Alto", "Categor\u00eda": "Tr\u00e1fico", "ID-Cat": 5200, "C\u00f3digo": 5203}}]}